infi.wmpio-0.1.31-py2.7-nspkg.pth
infi/wmpio/__init__.py
infi/wmpio/__version__.py
infi/wmpio/mpclaim/__init__.py
infi/wmpio/mpclaim/tests.py
infi/wmpio/scripts/__init__.py
infi/wmpio/wmi/__init__.py
infi/wmpio/wmi/model/__init__.py
infi/wmpio/wmi/model/tests.py
infi/wmpio/wmi/tests/__init__.py
infi.wmpio-0.1.31.dist-info/LICENSE
infi.wmpio-0.1.31.dist-info/METADATA
infi.wmpio-0.1.31.dist-info/WHEEL
infi.wmpio-0.1.31.dist-info/entry_points.txt
infi.wmpio-0.1.31.dist-info/namespace_packages.txt
infi.wmpio-0.1.31.dist-info/top_level.txt
infi.wmpio-0.1.31.dist-info/RECORD
