Metadata-Version: 2.1
Name: infi.wmpio
Version: 0.1.31
Summary: Windows MPIO Management in Python
Home-page: https://github.com/Infinidat/infi.wmpio
Author: Arnon Yaari
Author-email: arnony@infinidat.com
License: BSD
Platform: UNKNOWN
Classifier: Intended Audience :: Developers
Classifier: Intended Audience :: System Administrators
Classifier: License :: OSI Approved :: BSD License
Classifier: Operating System :: OS Independent
Classifier: Programming Language :: Python
Classifier: Programming Language :: Python :: 2
Classifier: Programming Language :: Python :: 3
Classifier: Topic :: Software Development :: Libraries :: Python Modules
Requires-Dist: infi.execute
Requires-Dist: infi.registry
Requires-Dist: infi.winver
Requires-Dist: infi.wmi
Requires-Dist: setuptools
